txpyfind/__init__.py
txpyfind/_version.py
txpyfind/client.py
txpyfind/parser.py
txpyfind/urlparse.py
txpyfind/utils.py
txpyfind-0.1.1.dist-info/LICENSE
txpyfind-0.1.1.dist-info/METADATA
txpyfind-0.1.1.dist-info/WHEEL
txpyfind-0.1.1.dist-info/top_level.txt
txpyfind-0.1.1.dist-info/RECORD
